reel44/__init__.py
reel44/enc_dec.py
reel44-1.0.1.dist-info/LICENSE
reel44-1.0.1.dist-info/METADATA
reel44-1.0.1.dist-info/WHEEL
reel44-1.0.1.dist-info/top_level.txt
reel44-1.0.1.dist-info/RECORD
