Metadata-Version: 2.1
Name: reel44
Version: 1.0.1
Summary: A Python Encryption Library BY-Keshri-InfoTech
Home-page: UNKNOWN
Author: Keshri-InfoTech
Author-email: keshrinfotech@gmail.com
License: UNKNOWN
Platform: UNKNOWN
Classifier: Programming Language :: Python :: 3
Classifier: License :: OSI Approved :: MIT License
Classifier: Operating System :: OS Independent
License-File: LICENSE
Requires-Dist: pyjwt
